stdkit/__init__.py
stdkit/chrono.py
stdkit/core.py
stdkit/exceptions.py
stdkit/py.typed
stdkit/rand.py
stdkit-0.3.0.dist-info/WHEEL
stdkit-0.3.0.dist-info/METADATA
stdkit-0.3.0.dist-info/RECORD
