Metadata-Version: 2.3
Name: stdkit
Version: 0.3.0
Summary: Standard library toolkit
Author: oyghen
Author-email: oyghen <oyghen@duck.com>
Requires-Python: >=3.11
